timench/__init__.py
timench/templates.py
timench/timench.py
timench-0.2.0.dist-info/LICENSE
timench-0.2.0.dist-info/METADATA
timench-0.2.0.dist-info/WHEEL
timench-0.2.0.dist-info/top_level.txt
timench-0.2.0.dist-info/RECORD
