Metadata-Version: 2.1
Name: timench
Version: 0.2.0
Summary: Timench is a small framework for measure execution time of one function, multiple functions and code
Home-page: https://github.com/ndrwpvlv/timench
Author: Andrei S. Pavlov
Author-email: ndrw.pvlv@gmail.com
License: MIT
Download-URL: https://github.com/ndrwpvlv/timench/archive/refs/tags/0.2.0.tar.gz
Keywords: time,measure execution time,measure time
Platform: UNKNOWN
Classifier: Programming Language :: Python :: 3.5
Classifier: Programming Language :: Python :: 3.6
Classifier: Programming Language :: Python :: 3.7
Classifier: Programming Language :: Python :: 3.8
Classifier: Programming Language :: Python :: 3.9
Classifier: Operating System :: OS Independent
Classifier: License :: OSI Approved :: MIT License
License-File: LICENSE
